hcli/__init__.py
hcli/env.py
hcli/main.py
hcli/commands/__init__.py
hcli/commands/commands.py
hcli/commands/common.py
hcli/commands/download.py
hcli/commands/login.py
hcli/commands/logout.py
hcli/commands/update.py
hcli/commands/whoami.py
hcli/commands/auth/__init__.py
hcli/commands/auth/default.py
hcli/commands/auth/list.py
hcli/commands/auth/switch.py
hcli/commands/auth/key/__init__.py
hcli/commands/auth/key/create.py
hcli/commands/auth/key/install.py
hcli/commands/auth/key/list.py
hcli/commands/auth/key/revoke.py
hcli/commands/extension/__init__.py
hcli/commands/extension/create.py
hcli/commands/extension/list.py
hcli/commands/ida/__init__.py
hcli/commands/ida/accept_eula.py
hcli/commands/ida/install.py
hcli/commands/ida/set_default.py
hcli/commands/ke/__init__.py
hcli/commands/ke/open.py
hcli/commands/ke/setup.py
hcli/commands/ke/ida/__init__.py
hcli/commands/ke/ida/add.py
hcli/commands/ke/ida/list.py
hcli/commands/ke/ida/remove.py
hcli/commands/ke/ida/switch.py
hcli/commands/ke/source/__init__.py
hcli/commands/ke/source/add.py
hcli/commands/ke/source/list.py
hcli/commands/ke/source/remove.py
hcli/commands/license/__init__.py
hcli/commands/license/common.py
hcli/commands/license/get.py
hcli/commands/license/install.py
hcli/commands/license/list.py
hcli/commands/plugin/__init__.py
hcli/commands/plugin/config.py
hcli/commands/plugin/install.py
hcli/commands/plugin/lint.py
hcli/commands/plugin/repo.py
hcli/commands/plugin/search.py
hcli/commands/plugin/status.py
hcli/commands/plugin/uninstall.py
hcli/commands/plugin/upgrade.py
hcli/commands/share/__init__.py
hcli/commands/share/delete.py
hcli/commands/share/get.py
hcli/commands/share/list.py
hcli/commands/share/put.py
hcli/lib/__init__.py
hcli/lib/console.py
hcli/lib/api/__init__.py
hcli/lib/api/asset.py
hcli/lib/api/auth.py
hcli/lib/api/common.py
hcli/lib/api/customer.py
hcli/lib/api/index.py
hcli/lib/api/keys.py
hcli/lib/api/license.py
hcli/lib/auth/__init__.py
hcli/lib/commands/__init__.py
ida_hcli-0.15.10.dist-info/licenses/LICENSE
ida_hcli-0.15.10.dist-info/METADATA
ida_hcli-0.15.10.dist-info/WHEEL
ida_hcli-0.15.10.dist-info/entry_points.txt
ida_hcli-0.15.10.dist-info/top_level.txt
ida_hcli-0.15.10.dist-info/RECORD
