Metadata-Version: 2.4
Name: ida-hcli
Version: 0.15.10
Summary: HCLI - Hex-Rays CLI Utility
Author-email: Hex-Rays SA <support@hex-rays.com>
License-Expression: MIT
Project-URL: Homepage, https://hex-rays.com/
Project-URL: Repository, https://github.com/HexRaysSA/ida-hcli
Project-URL: Issues, https://github.com/HexRaysSA/ida-hcli/issues
Keywords: ida,ida-pro,reverse-engineering,disassembler,binary-analysis,malware-analysis,security
Requires-Python: >=3.10
License-File: LICENSE
Requires-Dist: click
Requires-Dist: rich
Requires-Dist: rich-click
Requires-Dist: httpx
Requires-Dist: supabase
Requires-Dist: pydantic>=2.11.0
Requires-Dist: platformdirs
Requires-Dist: packaging
Requires-Dist: questionary
Requires-Dist: semantic-version>=2.10.0
Requires-Dist: requests>=2.32.4
Requires-Dist: idapro>=0.0.5
Requires-Dist: gotrue>=2.12.0
Requires-Dist: pip>=25.2
Requires-Dist: tomli>=1.2.0; python_version < "3.11"
Requires-Dist: pyyaml>=6.0.2
Requires-Dist: tenacity>=8.0.0
Provides-Extra: dev
Requires-Dist: taskipy>=1.14.1; extra == "dev"
Requires-Dist: python-semantic-release>=10.3.1; extra == "dev"
Provides-Extra: test
Requires-Dist: pytest>=7.0.0; extra == "test"
Requires-Dist: pytest-asyncio>=0.21.0; extra == "test"
Requires-Dist: pytest-mock>=3.10.0; extra == "test"
Requires-Dist: pytest-httpx>=0.21.0; extra == "test"
Requires-Dist: pexpect>=4.9.0; extra == "test"
Provides-Extra: docs
Requires-Dist: mkdocs-material; extra == "docs"
Requires-Dist: mkdocs-click>=0.9.0; extra == "docs"
Requires-Dist: mkdocstrings[python]>=0.20.0; extra == "docs"
Requires-Dist: mkdocs-gen-files>=0.5.0; extra == "docs"
Requires-Dist: mkdocs-include-markdown-plugin>=7.1.5; extra == "docs"
Requires-Dist: mkdocs-literate-nav>=0.6.2; extra == "docs"
Requires-Dist: pymdown-extensions>=10.15; extra == "docs"
Dynamic: license-file
